AUTHORS.rst
LICENSE
README.rst
setup.py
jaxtronomy/__init__.py
jaxtronomy.egg-info/PKG-INFO
jaxtronomy.egg-info/SOURCES.txt
jaxtronomy.egg-info/dependency_links.txt
jaxtronomy.egg-info/requires.txt
jaxtronomy.egg-info/top_level.txt
jaxtronomy/Data/__init__.py
jaxtronomy/Data/image_noise.py
jaxtronomy/Data/imaging_data.py
jaxtronomy/ImSim/__init__.py
jaxtronomy/ImSim/de_lens.py
jaxtronomy/ImSim/image_linear_solve.py
jaxtronomy/ImSim/image_model.py
jaxtronomy/ImSim/MultiBand/__init__.py
jaxtronomy/ImSim/MultiBand/single_band_multi_model.py
jaxtronomy/ImSim/Numerics/__init__.py
jaxtronomy/ImSim/Numerics/convolution.py
jaxtronomy/ImSim/Numerics/grid.py
jaxtronomy/ImSim/Numerics/numerics.py
jaxtronomy/ImSim/Numerics/numerics_subframe.py
jaxtronomy/ImSim/Numerics/point_source_rendering.py
jaxtronomy/LensModel/__init__.py
jaxtronomy/LensModel/lens_model.py
jaxtronomy/LensModel/lens_model_bulk.py
jaxtronomy/LensModel/profile_list_base.py
jaxtronomy/LensModel/single_plane.py
jaxtronomy/LensModel/single_plane_bulk.py
jaxtronomy/LensModel/LineOfSight/__init__.py
jaxtronomy/LensModel/LineOfSight/single_plane_los.py
jaxtronomy/LensModel/LineOfSight/LOSModels/__init__.py
jaxtronomy/LensModel/LineOfSight/LOSModels/los.py
jaxtronomy/LensModel/LineOfSight/LOSModels/los_minimal.py
jaxtronomy/LensModel/MultiPlane/__init__.py
jaxtronomy/LensModel/MultiPlane/decoupled_multi_plane.py
jaxtronomy/LensModel/MultiPlane/multi_plane.py
jaxtronomy/LensModel/MultiPlane/multi_plane_base.py
jaxtronomy/LensModel/MultiPlane/multi_plane_bulk.py
jaxtronomy/LensModel/Profiles/__init__.py
jaxtronomy/LensModel/Profiles/convergence.py
jaxtronomy/LensModel/Profiles/cored_steep_ellipsoid.py
jaxtronomy/LensModel/Profiles/epl.py
jaxtronomy/LensModel/Profiles/epl_multipole_m1m3m4.py
jaxtronomy/LensModel/Profiles/epl_multipole_m3m4.py
jaxtronomy/LensModel/Profiles/gaussian.py
jaxtronomy/LensModel/Profiles/gaussian_potential.py
jaxtronomy/LensModel/Profiles/hernquist.py
jaxtronomy/LensModel/Profiles/hernquist_ellipse_cse.py
jaxtronomy/LensModel/Profiles/multipole.py
jaxtronomy/LensModel/Profiles/nfw.py
jaxtronomy/LensModel/Profiles/nfw_ellipse_cse.py
