Metadata-Version: 2.1
Name: jaxtronomy
Version: 0.1.2
Summary: lenstronomy, but in JAX
Home-page: https://github.com/lenstronomy/JAXtronomy
Author: jaxtronomy developers
License: BSD-3
Keywords: jaxtronomy
Classifier: Development Status :: 5 - Production/Stable
Classifier: Intended Audience :: Science/Research
Classifier: Natural Language :: English
Classifier: Operating System :: OS Independent
Classifier: Programming Language :: Python
Classifier: Programming Language :: Python :: 3.11
Requires-Python: >=3.11
License-File: LICENSE
License-File: AUTHORS.rst
